<?xml version="1.0" encoding="UTF-8"?>
<BaliMessageLog>
    <Task name="Lattice_Synthesis">
        <Message>
            <ID>35002000</ID>
            <Severity>Info</Severity>
        </Message>
        <Message>
            <ID>35001781</ID>
            <Severity>Info</Severity>
        </Message>
        <Message>
            <ID>35901320</ID>
            <Severity>Warning</Severity>
            <Dynamic>d:/rtl_fpga/verilog/aula26_datapath/impl1/source/ula2.v(19): </Dynamic>
            <Navigation>d:/rtl_fpga/verilog/aula26_datapath/impl1/source/ula2.v</Navigation>
            <Navigation>19</Navigation>
        </Message>
        <Message>
            <ID>35901320</ID>
            <Severity>Warning</Severity>
            <Dynamic>d:/rtl_fpga/verilog/aula26_datapath/impl1/source/ula2.v(20): </Dynamic>
            <Navigation>d:/rtl_fpga/verilog/aula26_datapath/impl1/source/ula2.v</Navigation>
            <Navigation>20</Navigation>
        </Message>
        <Message>
            <ID>35901018</ID>
            <Severity>Info</Severity>
            <Dynamic>d:/rtl_fpga/verilog/aula26_datapath/top_model.v(1): </Dynamic>
            <Dynamic>datapath</Dynamic>
            <Navigation>d:/rtl_fpga/verilog/aula26_datapath/top_model.v</Navigation>
            <Navigation>1</Navigation>
        </Message>
        <Message>
            <ID>35901018</ID>
            <Severity>Info</Severity>
            <Dynamic>d:/rtl_fpga/verilog/aula26_datapath/mux21.v(1): </Dynamic>
            <Dynamic>mux21</Dynamic>
            <Navigation>d:/rtl_fpga/verilog/aula26_datapath/mux21.v</Navigation>
            <Navigation>1</Navigation>
        </Message>
        <Message>
            <ID>35901018</ID>
            <Severity>Info</Severity>
            <Dynamic>d:/rtl_fpga/verilog/aula26_datapath/reg_4bits.v(1): </Dynamic>
            <Dynamic>reg_4bits</Dynamic>
            <Navigation>d:/rtl_fpga/verilog/aula26_datapath/reg_4bits.v</Navigation>
            <Navigation>1</Navigation>
        </Message>
        <Message>
            <ID>35901018</ID>
            <Severity>Info</Severity>
            <Dynamic>d:/rtl_fpga/verilog/aula26_datapath/demux12.v(1): </Dynamic>
            <Dynamic>demux12</Dynamic>
            <Navigation>d:/rtl_fpga/verilog/aula26_datapath/demux12.v</Navigation>
            <Navigation>1</Navigation>
        </Message>
        <Message>
            <ID>35901018</ID>
            <Severity>Info</Severity>
            <Dynamic>d:/rtl_fpga/verilog/aula26_datapath/flipflop_d.v(1): </Dynamic>
            <Dynamic>flipflop_D</Dynamic>
            <Navigation>d:/rtl_fpga/verilog/aula26_datapath/flipflop_d.v</Navigation>
            <Navigation>1</Navigation>
        </Message>
        <Message>
            <ID>35901320</ID>
            <Severity>Warning</Severity>
            <Dynamic>d:/rtl_fpga/verilog/aula26_datapath/impl1/source/ula2.v(19): </Dynamic>
            <Navigation>d:/rtl_fpga/verilog/aula26_datapath/impl1/source/ula2.v</Navigation>
            <Navigation>19</Navigation>
        </Message>
        <Message>
            <ID>35901320</ID>
            <Severity>Warning</Severity>
            <Dynamic>d:/rtl_fpga/verilog/aula26_datapath/impl1/source/ula2.v(20): </Dynamic>
            <Navigation>d:/rtl_fpga/verilog/aula26_datapath/impl1/source/ula2.v</Navigation>
            <Navigation>20</Navigation>
        </Message>
        <Message>
            <ID>35901018</ID>
            <Severity>Info</Severity>
            <Dynamic>d:/rtl_fpga/verilog/aula26_datapath/impl1/source/ula2.v(1): </Dynamic>
            <Dynamic>ula_ula2</Dynamic>
            <Navigation>d:/rtl_fpga/verilog/aula26_datapath/impl1/source/ula2.v</Navigation>
            <Navigation>1</Navigation>
        </Message>
        <Message>
            <ID>35901209</ID>
            <Severity>Warning</Severity>
            <Dynamic>d:/rtl_fpga/verilog/aula26_datapath/impl1/source/ula2.v(19): </Dynamic>
            <Dynamic>35</Dynamic>
            <Dynamic>4</Dynamic>
            <Navigation>d:/rtl_fpga/verilog/aula26_datapath/impl1/source/ula2.v</Navigation>
            <Navigation>19</Navigation>
        </Message>
        <Message>
            <ID>35001747</ID>
            <Severity>Warning</Severity>
            <Dynamic>3</Dynamic>
            <Dynamic>\regB/Q</Dynamic>
        </Message>
        <Message>
            <ID>35001747</ID>
            <Severity>Warning</Severity>
            <Dynamic>2</Dynamic>
            <Dynamic>\regB/Q</Dynamic>
        </Message>
        <Message>
            <ID>35001747</ID>
            <Severity>Warning</Severity>
            <Dynamic>1</Dynamic>
            <Dynamic>\regB/Q</Dynamic>
        </Message>
        <Message>
            <ID>35002005</ID>
            <Severity>Warning</Severity>
            <Dynamic>dados[3]</Dynamic>
        </Message>
        <Message>
            <ID>35002005</ID>
            <Severity>Warning</Severity>
            <Dynamic>dados[2]</Dynamic>
        </Message>
        <Message>
            <ID>35002005</ID>
            <Severity>Warning</Severity>
            <Dynamic>dados[1]</Dynamic>
        </Message>
        <Message>
            <ID>35002005</ID>
            <Severity>Warning</Severity>
            <Dynamic>dados[0]</Dynamic>
        </Message>
        <Message>
            <ID>35002005</ID>
            <Severity>Warning</Severity>
            <Dynamic>sel21</Dynamic>
        </Message>
        <Message>
            <ID>35935013</ID>
            <Severity>Warning</Severity>
            <Dynamic>d:/rtl_fpga/verilog/aula26_datapath/reg_4bits.v(30): </Dynamic>
            <Dynamic>\rf/data_out__i1</Dynamic>
            <Navigation>d:/rtl_fpga/verilog/aula26_datapath/reg_4bits.v</Navigation>
            <Navigation>30</Navigation>
        </Message>
        <Message>
            <ID>35935013</ID>
            <Severity>Warning</Severity>
            <Dynamic>d:/rtl_fpga/verilog/aula26_datapath/flipflop_d.v(13): </Dynamic>
            <Dynamic>\regA/Q__i1</Dynamic>
            <Navigation>d:/rtl_fpga/verilog/aula26_datapath/flipflop_d.v</Navigation>
            <Navigation>13</Navigation>
        </Message>
        <Message>
            <ID>35001611</ID>
            <Severity>Warning</Severity>
        </Message>
        <Message>
            <ID>1166052</ID>
            <Severity>Warning</Severity>
            <Dynamic>logical</Dynamic>
            <Dynamic>dados[3]</Dynamic>
            <Navigation>dados[3]</Navigation>
        </Message>
        <Message>
            <ID>1166064</ID>
            <Severity>Warning</Severity>
            <Dynamic>input</Dynamic>
            <Dynamic>dados[3]</Dynamic>
        </Message>
        <Message>
            <ID>1166052</ID>
            <Severity>Warning</Severity>
            <Dynamic>logical</Dynamic>
            <Dynamic>dados[2]</Dynamic>
            <Navigation>dados[2]</Navigation>
        </Message>
        <Message>
            <ID>1166064</ID>
            <Severity>Warning</Severity>
            <Dynamic>input</Dynamic>
            <Dynamic>dados[2]</Dynamic>
        </Message>
        <Message>
            <ID>1166052</ID>
            <Severity>Warning</Severity>
            <Dynamic>logical</Dynamic>
            <Dynamic>dados[1]</Dynamic>
            <Navigation>dados[1]</Navigation>
        </Message>
        <Message>
            <ID>1166064</ID>
            <Severity>Warning</Severity>
            <Dynamic>input</Dynamic>
            <Dynamic>dados[1]</Dynamic>
        </Message>
        <Message>
            <ID>1166052</ID>
            <Severity>Warning</Severity>
            <Dynamic>logical</Dynamic>
            <Dynamic>dados[0]</Dynamic>
            <Navigation>dados[0]</Navigation>
        </Message>
        <Message>
            <ID>1166064</ID>
            <Severity>Warning</Severity>
            <Dynamic>input</Dynamic>
            <Dynamic>dados[0]</Dynamic>
        </Message>
        <Message>
            <ID>1166052</ID>
            <Severity>Warning</Severity>
            <Dynamic>logical</Dynamic>
            <Dynamic>sel21</Dynamic>
            <Navigation>sel21</Navigation>
        </Message>
        <Message>
            <ID>1166064</ID>
            <Severity>Warning</Severity>
            <Dynamic>input</Dynamic>
            <Dynamic>sel21</Dynamic>
        </Message>
        <Message>
            <ID>1166052</ID>
            <Severity>Warning</Severity>
            <Dynamic>logical</Dynamic>
            <Dynamic>escrita_c</Dynamic>
            <Navigation>escrita_c</Navigation>
        </Message>
        <Message>
            <ID>1166052</ID>
            <Severity>Warning</Severity>
            <Dynamic>logical</Dynamic>
            <Dynamic>clk_c</Dynamic>
            <Navigation>clk_c</Navigation>
        </Message>
        <Message>
            <ID>1166052</ID>
            <Severity>Warning</Severity>
            <Dynamic>logical</Dynamic>
            <Dynamic>sel12_c</Dynamic>
            <Navigation>sel12_c</Navigation>
        </Message>
        <Message>
            <ID>1166052</ID>
            <Severity>Warning</Severity>
            <Dynamic>logical</Dynamic>
            <Dynamic>Cin_c</Dynamic>
            <Navigation>Cin_c</Navigation>
        </Message>
        <Message>
            <ID>1166052</ID>
            <Severity>Warning</Severity>
            <Dynamic>logical</Dynamic>
            <Dynamic>reset_c</Dynamic>
            <Navigation>reset_c</Navigation>
        </Message>
        <Message>
            <ID>1166052</ID>
            <Severity>Warning</Severity>
            <Dynamic>logical</Dynamic>
            <Dynamic>addr_c_0</Dynamic>
            <Navigation>addr_c_0</Navigation>
        </Message>
        <Message>
            <ID>1166052</ID>
            <Severity>Warning</Severity>
            <Dynamic>logical</Dynamic>
            <Dynamic>addr_c_1</Dynamic>
            <Navigation>addr_c_1</Navigation>
        </Message>
        <Message>
            <ID>1166052</ID>
            <Severity>Warning</Severity>
            <Dynamic>logical</Dynamic>
            <Dynamic>operacao_c_0</Dynamic>
            <Navigation>operacao_c_0</Navigation>
        </Message>
        <Message>
            <ID>1163101</ID>
            <Severity>Warning</Severity>
            <Dynamic>18</Dynamic>
        </Message>
    </Task>
</BaliMessageLog>